{
  "parent": "prehistoricfauna:prehistoricfauna/recipes/root",
  "rewards": {
    "recipes": [
      "prehistoricfauna:cooked_dakotaraptor_meat"
    ]
  },
  "criteria": {
    "has_meat": {
      "trigger": "minecraft:inventory_changed",
      "conditions": {
        "items": [
          {
            "item": "prehistoricfauna:raw_dakotaraptor_meat"
          }
        ]
      }
    },
    "has_the_recipe": {
      "trigger": "minecraft:recipe_unlocked",
      "conditions": {
        "recipe": "prehistoricfauna:cooked_dakotaraptor_meat"
      }
    }
  },
  "requirements": [
    [
      "has_meat",
      "has_the_recipe"
    ]
  ]
}