{
  "type": "minecraft:entity",
  "pools": [
    {
      "rolls": 1,
      "entries": [
        {
          "type": "minecraft:item",
          "name": "prehistoricfauna:henostone",
          "functions": [
            {
              "function": "minecraft:set_count",
              "count": {
                "min": 0,
                "max": 8
              }
            }
          ]
        }
      ]
    },
    {
      "rolls": 1,
      "bonus_rolls": 0,
      "entries": [
        {
          "type": "minecraft:item",
          "name": "prehistoricfauna:time_totem",
          "functions": [
            {
              "function": "minecraft:set_count",
              "count": 1
            }
          ]
        }
      ]
    }
  ]
}